surrantic/__init__.py
surrantic/base.py
surrantic/logging_config.py
surrantic/py.typed
surrantic-0.2.2.dist-info/METADATA
surrantic-0.2.2.dist-info/WHEEL
surrantic-0.2.2.dist-info/licenses/LICENSE
surrantic-0.2.2.dist-info/RECORD
