Metadata-Version: 2.4
Name: surrantic
Version: 0.2.2
Summary: A simple Pydantic ORM implementation for SurrealDB
Project-URL: Homepage, https://github.com/lfnovo/surrantic
Project-URL: Repository, https://github.com/lfnovo/surrantic.git
Project-URL: Documentation, https://github.com/lfnovo/surrantic#readme
Project-URL: Bug Tracker, https://github.com/lfnovo/surrantic/issues
Author-email: LUIS NOVO <lfnovo@gmail.com>
License: MIT
License-File: LICENSE
Classifier: Development Status :: 4 - Beta
Classifier: Intended Audience :: Developers
Classifier: License :: OSI Approved :: MIT License
Classifier: Operating System :: OS Independent
Classifier: Programming Language :: Python :: 3
Classifier: Programming Language :: Python :: 3.10
Classifier: Programming Language :: Python :: 3.11
Classifier: Topic :: Database
Classifier: Topic :: Software Development :: Libraries :: Python Modules
Requires-Python: >=3.10
Requires-Dist: pydantic>=2.0.0
Requires-Dist: python-dotenv>=1.0.0
Requires-Dist: surrealdb==0.4.1
